winrt/_winrt_windows_ui_core_preview_communications.cp313-win_arm64.pyd
winrt/_winrt_windows_ui_core_preview_communications.pyi
winrt/windows/ui/core/preview/communications/__init__.py
winrt/windows/ui/core/preview/communications/py.typed
winrt_Windows.UI.Core.Preview.Communications-2.2.0.dist-info/METADATA
winrt_Windows.UI.Core.Preview.Communications-2.2.0.dist-info/WHEEL
winrt_Windows.UI.Core.Preview.Communications-2.2.0.dist-info/top_level.txt
winrt_Windows.UI.Core.Preview.Communications-2.2.0.dist-info/RECORD
